{"cameraMode":{"drawMode":0,"name":"Shaded","section":"Shading Mode"},"sceneLighting":true,"audioPlay":false,"sceneViewState":{"m_AlwaysRefresh":true,"showFog":true,"showSkybox":true,"showFlares":true,"showImageEffects":true,"showParticleSystems":true,"showVisualEffectGraphs":true,"m_FxEnabled":true},"in2DMode":false,"pivot":{"x":514.1478881835938,"y":1.8834656476974488,"z":476.9947204589844},"rotation":{"x":-0.08837728947401047,"y":0.5192698836326599,"z":-0.05410735681653023,"w":-0.8483284115791321},"size":4.399324893951416,"orthographic":false}